{ "format_version": "0.1", "terraform_version": "0.14.3", "planned_values": { "root_module": { "resources": [ { "address": "local_file.test", "mode": "managed", "type": "local_file", "name": "test", "provider_name": "registry.terraform.io/hashicorp/local", "schema_version": 0, "values": { "content": "example", "content_base64": null, "directory_permission": "0777", "file_permission": "0777", "filename": "./example", "sensitive_content": null, "source": null } } ] } }, "resource_changes": [ { "address": "local_file.main", "mode": "managed", "type": "local_file", "name": "main", "provider_name": "registry.terraform.io/hashicorp/local", "change": { "actions": [ "delete" ], "before": { "content": "example", "content_base64": null, "directory_permission": "0777", "file_permission": "0777", "filename": "./example", "id": "c3499c2729730a7f807efb8676a92dcb6f8a3f8f", "sensitive_content": null, "source": null }, "after": null, "after_unknown": {} } }, { "address": "local_file.test", "mode": "managed", "type": "local_file", "name": "test", "provider_name": "registry.terraform.io/hashicorp/local", "change": { "actions": [ "create" ], "before": null, "after": { "content": "example", "content_base64": null, "directory_permission": "0777", "file_permission": "0777", "filename": "./example", "sensitive_content": null, "source": null }, "after_unknown": { "id": true } } } ], "prior_state": { "format_version": "0.1", "terraform_version": "0.14.3", "values": { "root_module": { "resources": [ { "address": "local_file.main", "mode": "managed", "type": "local_file", "name": "main", "provider_name": "registry.terraform.io/hashicorp/local", "schema_version": 0, "values": { "content": "example", "content_base64": null, "directory_permission": "0777", "file_permission": "0777", "filename": "./example", "id": "c3499c2729730a7f807efb8676a92dcb6f8a3f8f", "sensitive_content": null, "source": null } } ] } } }, "configuration": { "root_module": { "resources": [ { "address": "local_file.test", "mode": "managed", "type": "local_file", "name": "test", "provider_config_key": "local", "expressions": { "content": { "constant_value": "example" }, "filename": { "references": [ "path.module" ] } }, "schema_version": 0 } ] } } }
